llm_cmd_comp/__init__.py
llm_cmd_comp/share/llm-cmd-comp.bash
llm_cmd_comp/share/llm-cmd-comp.fish
llm_cmd_comp/share/llm-cmd-comp.zsh
llm_cmd_comp-1.2.0.dist-info/licenses/LICENSE
llm_cmd_comp-1.2.0.dist-info/METADATA
llm_cmd_comp-1.2.0.dist-info/WHEEL
llm_cmd_comp-1.2.0.dist-info/entry_points.txt
llm_cmd_comp-1.2.0.dist-info/top_level.txt
llm_cmd_comp-1.2.0.dist-info/RECORD
