Metadata-Version: 2.4
Name: llm-cmd-comp
Version: 1.2.0
Summary: Use LLM to generate commands for your shell
Author: Ryan Patterson
License-Expression: Apache-2.0
Project-URL: Homepage, https://github.com/CGamesPlay/llm-cmd-comp
Project-URL: Changelog, https://github.com/CGamesPlay/llm-cmd-comp/releases
Project-URL: Issues, https://github.com/CGamesPlay/llm-cmd-comp/issues
License-File: LICENSE
Requires-Dist: llm
Requires-Dist: prompt_toolkit>=3.0.43
Dynamic: license-file
